LICENSE
MANIFEST.in
README.rst
requests_twisted.py
setup.py
tests.py
requests_twisted.egg-info/PKG-INFO
requests_twisted.egg-info/SOURCES.txt
requests_twisted.egg-info/dependency_links.txt
requests_twisted.egg-info/not-zip-safe
requests_twisted.egg-info/requires.txt
requests_twisted.egg-info/top_level.txt