Metadata-Version: 1.1
Name: requests-twisted
Version: 0.1.2
Summary: Twisted adapter for the requests library.
Home-page: https://github.com/sametmax/requests-twisted
Author: Sam et Max
Author-email: lesametlemax@gmail.com
License: Zlib Licence
Platform: UNKNOWN
Classifier: Intended Audience :: Developers
Classifier: Natural Language :: English
Classifier: Programming Language :: Python
Classifier: Programming Language :: Python :: 2.7
